distributed_random_forest/__init__.py
distributed_random_forest/data/__init__.py
distributed_random_forest/experiments/__init__.py
distributed_random_forest/experiments/exp1_hparams.py
distributed_random_forest/experiments/exp2_clients.py
distributed_random_forest/experiments/exp3_global_rf.py
distributed_random_forest/experiments/exp4_dp_rf.py
distributed_random_forest/federation/__init__.py
distributed_random_forest/federation/aggregator.py
distributed_random_forest/federation/voting.py
distributed_random_forest/models/__init__.py
distributed_random_forest/models/dp_rf.py
distributed_random_forest/models/random_forest.py
distributed_random_forest/models/tree_utils.py
distributed_random_forest-0.0.3.dist-info/licenses/LICENSE
distributed_random_forest-0.0.3.dist-info/METADATA
distributed_random_forest-0.0.3.dist-info/WHEEL
distributed_random_forest-0.0.3.dist-info/top_level.txt
distributed_random_forest-0.0.3.dist-info/RECORD
