Metadata-Version: 2.4
Name: distributed-random-forest
Version: 0.0.3
Summary: Distributed/Federated Random Forest framework with Differential Privacy support
Author: Bowenislandsong
License:                                  Apache License
Project-URL: Homepage, https://github.com/Bowenislandsong/distributed_random_forest
Project-URL: Repository, https://github.com/Bowenislandsong/distributed_random_forest
Project-URL: Issues, https://github.com/Bowenislandsong/distributed_random_forest/issues
Keywords: machine-learning,random-forest,federated-learning,differential-privacy,distributed-computing
Classifier: Development Status :: 3 - Alpha
Classifier: Intended Audience :: Developers
Classifier: Intended Audience :: Science/Research
Classifier: License :: OSI Approved :: Apache Software License
Classifier: Operating System :: OS Independent
Classifier: Programming Language :: Python :: 3
Classifier: Programming Language :: Python :: 3.8
Classifier: Programming Language :: Python :: 3.9
Classifier: Programming Language :: Python :: 3.10
Classifier: Programming Language :: Python :: 3.11
Classifier: Programming Language :: Python :: 3.12
Classifier: Topic :: Scientific/Engineering :: Artificial Intelligence
Requires-Python: >=3.8
License-File: LICENSE
Requires-Dist: numpy>=1.21.0
Requires-Dist: scikit-learn>=1.0.0
Requires-Dist: pandas>=1.3.0
Requires-Dist: diffprivlib>=0.6.0
Provides-Extra: dev
Requires-Dist: pytest>=7.0.0; extra == "dev"
Requires-Dist: pytest-cov>=4.0.0; extra == "dev"
Dynamic: license-file
